ebics_api_client/__init__.py
ebics_api_client/ebics_api_client.py
ebics_api_client-1.0.9.dist-info/LICENSE
ebics_api_client-1.0.9.dist-info/METADATA
ebics_api_client-1.0.9.dist-info/WHEEL
ebics_api_client-1.0.9.dist-info/top_level.txt
ebics_api_client-1.0.9.dist-info/RECORD
