Metadata-Version: 2.1
Name: ebics-api-client
Version: 1.0.9
Summary: EBICS API Client
Home-page: https://github.com/andrew-svirin/ebics-api-client-python
Author: Andrew Svirin
Author-email: andrey.svirin@ukr.net
License: MIT
Platform: UNKNOWN
Classifier: Programming Language :: Python :: 3
Classifier: License :: OSI Approved :: MIT License
Classifier: Operating System :: OS Independent
Requires-Python: >=3.6
License-File: LICENSE
Requires-Dist: requests
Requires-Dist: python-dotenv
